microscopemetrics_omero/__init__.py
microscopemetrics_omero/dump.py
microscopemetrics_omero/load.py
microscopemetrics_omero/omero_tools.py
microscopemetrics_omero/process.py
microscopemetrics_omero-0.2.0.dist-info/LICENSE
microscopemetrics_omero-0.2.0.dist-info/METADATA
microscopemetrics_omero-0.2.0.dist-info/WHEEL
microscopemetrics_omero-0.2.0.dist-info/RECORD
